limecore/database/api/__init__.py
limecore/database/api/database.py
limecore/database/api/result.py
limecore/database/api/row.py
limecore_database_api-0.1.0.dist-info/LICENSE.txt
limecore_database_api-0.1.0.dist-info/METADATA
limecore_database_api-0.1.0.dist-info/WHEEL
limecore_database_api-0.1.0.dist-info/top_level.txt
limecore_database_api-0.1.0.dist-info/RECORD
