Metadata-Version: 2.1
Name: limecore-database-api
Version: 0.1.0
Summary: limecore: Database API
Home-page: https://github.com/limecore/database-api
Author: Daniel Bradberry
Author-email: daniel@danielbradberry.com
License: MIT
Platform: UNKNOWN
Classifier: Programming Language :: Python :: 3
Classifier: License :: OSI Approved :: MIT License
Classifier: Operating System :: OS Independent
Requires-Python: >=3.7
